LICENSE
MANIFEST.in
README.md
setup.cfg
setup.py
pragyaniitian/__init__.py
pragyaniitian.egg-info/PKG-INFO
pragyaniitian.egg-info/SOURCES.txt
pragyaniitian.egg-info/dependency_links.txt
pragyaniitian.egg-info/requires.txt
pragyaniitian.egg-info/top_level.txt
pragyaniitian/blacklist/__init__.py
pragyaniitian/blacklist/support.py
pragyaniitian/button/__init__.py
pragyaniitian/button/button.py
pragyaniitian/extra/__init__.py
pragyaniitian/extra/hosted.py
pragyaniitian/help/__init__.py
pragyaniitian/help/help.py
pragyaniitian/helper/__init__.py
pragyaniitian/helper/basic.py
pragyaniitian/helper/call.py
pragyaniitian/helper/check_size.py
pragyaniitian/helper/clear_string.py
pragyaniitian/helper/content.py
pragyaniitian/helper/data.py
pragyaniitian/helper/dl_helpers.py
pragyaniitian/helper/goblok.py
pragyaniitian/helper/hacking.py
pragyaniitian/helper/inline.py
pragyaniitian/helper/interval.py
pragyaniitian/helper/parser.py
pragyaniitian/helper/pragyan.py
pragyaniitian/helper/repo.py
pragyaniitian/helper/sticker.py
pragyaniitian/helper/tools.py
pragyaniitian/helper/utility.py
pragyaniitian/helper/what.py
pragyaniitian/methods/__init__.py
pragyaniitian/methods/queue.py
pragyaniitian/openai/__init__.py
pragyaniitian/openai/create.py
pragyaniitian/py_trans/__init__.py
pragyaniitian/py_trans/async_translator.py
pragyaniitian/py_trans/errors.py
pragyaniitian/py_trans/language_codes.py
pragyaniitian/py_trans/translator.py
pragyaniitian/pyrogram/__init__.py
pragyaniitian/pyrogram/_wrappers.py
pragyaniitian/pyrogram/func.py
pragyaniitian/pyrogram/misc.py
pragyaniitian/pyrogram/sections.py
pragyaniitian/pyrogram/toolbot.py
pragyaniitian/pyrogram/tools.py
pragyaniitian/types/__init__.py
pragyaniitian/types/mod.py