Metadata-Version: 2.1
Name: pragyaniitian
Version: 0.1.27
Summary: PragyanIITIAN Userbot 
Home-page: https://github.com/PragyanIITIAN
Author: PragyanIITIAN
Author-email: pragyaniitian@gmail.com
License: MIT
Classifier: License :: OSI Approved :: MIT License
Classifier: Programming Language :: Python
Classifier: Programming Language :: Python :: 3
Classifier: Programming Language :: Python :: 3.6
Classifier: Programming Language :: Python :: 3.7
Classifier: Programming Language :: Python :: 3.8
Classifier: Programming Language :: Python :: Implementation :: CPython
Classifier: Programming Language :: Python :: Implementation :: PyPy
Requires-Python: ~=3.8,~=3.9
License-File: LICENSE
